MANIFEST.in
README.rst
requirements.txt
setup.py
cld2/__init__.py
cld2/binding.cc
cld2/binding.h
cld2/binding_decls.h
cld2/encoding_lut.cc
cld2/__pycache__/_cffi__x9a179be0x35bf7e70.c
cld2/__pycache__/_cffi__xbc04ae64x1977d085.c
cld2/internal/cld2_dynamic_compat.h
cld2/internal/cld2_dynamic_data.h
cld2/internal/cld2_dynamic_data_extractor.h
cld2/internal/cld2_dynamic_data_loader.h
cld2/internal/cld2_generated_cjk_compatible.cc
cld2/internal/cld2_generated_deltaocta0122.cc
cld2/internal/cld2_generated_deltaoctachrome.cc
cld2/internal/cld2_generated_distinctocta0122.cc
cld2/internal/cld2_generated_distinctoctachrome.cc
cld2/internal/cld2_generated_quad0122.cc
cld2/internal/cld2_generated_quadchrome_2.cc
cld2/internal/cld2tablesummary.h
cld2/internal/cld_generated_cjk_delta_bi_32.cc
cld2/internal/cld_generated_cjk_delta_bi_4.cc
cld2/internal/cld_generated_cjk_uni_prop_80.cc
cld2/internal/cld_generated_score_quad_octa_0122.cc
cld2/internal/cld_generated_score_quad_octa_2.cc
cld2/internal/cldutil.cc
cld2/internal/cldutil.h
cld2/internal/cldutil_offline.h
cld2/internal/cldutil_shared.cc
cld2/internal/cldutil_shared.h
cld2/internal/compact_lang_det.cc
cld2/internal/compact_lang_det_hint_code.cc
cld2/internal/compact_lang_det_hint_code.h
cld2/internal/compact_lang_det_impl.cc
cld2/internal/compact_lang_det_impl.h
cld2/internal/debug.cc
cld2/internal/debug.h
cld2/internal/fixunicodevalue.cc
cld2/internal/fixunicodevalue.h
cld2/internal/generated_distinct_bi_0.cc
cld2/internal/generated_entities.cc
cld2/internal/generated_language.cc
cld2/internal/generated_language.h
cld2/internal/generated_ulscript.cc
cld2/internal/generated_ulscript.h
cld2/internal/getonescriptspan.cc
cld2/internal/getonescriptspan.h
cld2/internal/integral_types.h
cld2/internal/lang_script.cc
cld2/internal/lang_script.h
cld2/internal/langspan.h
cld2/internal/offsetmap.cc
cld2/internal/offsetmap.h
cld2/internal/port.h
cld2/internal/scoreonescriptspan.cc
cld2/internal/scoreonescriptspan.h
cld2_cffi.egg-info/PKG-INFO
cld2_cffi.egg-info/SOURCES.txt
cld2_cffi.egg-info/dependency_links.txt
cld2_cffi.egg-info/not-zip-safe
cld2_cffi.egg-info/requires.txt
cld2_cffi.egg-info/top_level.txt
