Metadata-Version: 1.1
Name: cld2-cffi
Version: 0.1.3
Summary: CFFI bindings around Google Chromium's embedded compact language detection library (CLD2)
Home-page: http://github.com/GregBowyer/cld2-cffi/
Author: Michael McCandless & Greg Bowyer
Author-email: mail@mikemccandless.com & gbowyer@fastmail.co.uk
License: Apache2
Keywords: cld2,cffi
Platform: UNKNOWN
Classifier: License :: OSI Approved :: BSD License
Classifier: Operating System :: MacOS :: MacOS X
Classifier: Operating System :: Microsoft :: Windows
Classifier: Operating System :: POSIX :: Linux
Classifier: Programming Language :: C++
Classifier: Programming Language :: Python
Classifier: Programming Language :: Python :: Implementation :: CPython
Classifier: Programming Language :: Python :: Implementation :: PyPy
Classifier: Development Status :: 4 - Beta
Classifier: Intended Audience :: Developers
Classifier: Topic :: Text Processing :: Linguistic
